unirange/__init__.py
unirange/__main__.py
unirange-1.0.dist-info/LICENSE.txt
unirange-1.0.dist-info/METADATA
unirange-1.0.dist-info/WHEEL
unirange-1.0.dist-info/top_level.txt
unirange-1.0.dist-info/RECORD
