Metadata-Version: 2.1
Name: unirange
Version: 1.0
Summary: Unirange is a notation for specifying multiple Unicode codepoints.
Author: WhoAteMyButter
License: MIT
Project-URL: Source, https://gitlab.com/whoatemybutter/unirange
Project-URL: Changelog, https://gitlab.com/whoatemybutter/unirange/-/blob/master/CHANGELOG.md
Project-URL: Issues, https://gitlab.com/whoatemybutter/unirange/-/issues
Keywords: unicode,characters,range,unirange
Classifier: Programming Language :: Python :: 3
Classifier: Programming Language :: Python :: 3 :: Only
Classifier: Programming Language :: Python :: 3.11
Classifier: Operating System :: OS Independent
Classifier: Topic :: Text Processing
Classifier: Topic :: Utilities
Classifier: Typing :: Typed
Classifier: Development Status :: 4 - Beta
Classifier: Intended Audience :: Other Audience
Classifier: Intended Audience :: Developers
Classifier: License :: OSI Approved :: MIT License
Classifier: Natural Language :: English
Requires-Python: >=3.11
License-File: LICENSE.txt
